{
    "Params": {
        "SupplyChainRelationshipID": 100000000,
        "Buyer":101,
        "Seller":201,
        "UserID":"101@gmail.com",
        "User":"buyer",
        "businessPartner": 101,
        "IsMarkedForDeletion": false
    },
    "runtime_session_id": "cc45f715586040f8b902f405eb1e9fdd",
    "ui_function": "PriceMasterDetailList",
    "ui_key_function_url": "101@gmail.com/priceMaster/detail/list/user=buyer",
    "ui_key_general_business_partner": "priceMaster/list/businessPartnerID=101",
    "ui_key_general_user_id": "priceMaster/list/userID=101@gmail.com",
    "ui_key_general_user_language": "priceMaster/list/language=JA"
  }